kniteditor/AYABKnitSettings.py
kniteditor/AYABKnitter.py
kniteditor/EditorWindow.py
kniteditor/InstructionSVGWidgetCache.py
kniteditor/IntInput.py
kniteditor/KnittingPatternWidget.py
kniteditor/__init__.py
kniteditor/__main__.py
kniteditor/dialogs.py
kniteditor/editorwindow.kv
kniteditor/settings.py
kniteditor/localization/__init__.py
kniteditor/localization/observable_translation.py
kniteditor/localization/test/test_localization.py
kniteditor/localization/test/test_translations.py
kniteditor/localization/translations/de/LC_MESSAGES/kniteditor.mo
kniteditor/localization/translations/en/LC_MESSAGES/kniteditor.mo
kniteditor/localization/translations/languages/LC_MESSAGES/languages.mo
kniteditor/localization/translations/ru/LC_MESSAGES/kniteditor.mo
kniteditor/test/conftest.py
kniteditor/test/test_can_import.py
kniteditor-1.0.5.dist-info/DESCRIPTION.rst
kniteditor-1.0.5.dist-info/METADATA
kniteditor-1.0.5.dist-info/RECORD
kniteditor-1.0.5.dist-info/WHEEL
kniteditor-1.0.5.dist-info/metadata.json
kniteditor-1.0.5.dist-info/top_level.txt
