Metadata-Version: 2.0
Name: kniteditor
Version: 1.0.5
Summary: An editor for knitwork.
Home-page: https://github.com/fossasia/kniteditor
Author: Nicco Kunzmann
Author-email: niccokunzmann@rambler.ru
License: LGPL
Keywords: knitting ayab fashion
Platform: UNKNOWN
Classifier: Intended Audience :: Developers
Classifier: License :: OSI Approved :: GNU Lesser General Public License v3 (LGPLv3)
Classifier: Topic :: Software Development :: Libraries :: Python Modules
Classifier: Topic :: Artistic Software
Classifier: Topic :: Home Automation
Classifier: Topic :: Utilities
Classifier: Intended Audience :: Manufacturing
Classifier: Natural Language :: English
Classifier: Operating System :: OS Independent
Classifier: Programming Language :: Python :: 3 :: Only
Classifier: Development Status :: 5 - Production/Stable
Requires-Dist: AYABInterface (==0.0.9)
Requires-Dist: ObservableList (==0.0.2)
Requires-Dist: Pillow (==3.2.0)
Requires-Dist: crc8 (==0.0.3)
Requires-Dist: knittingpattern (==0.1.19)
Requires-Dist: pyserial (==3.1.1)
Requires-Dist: webcolors (==1.5)
Requires-Dist: xmltodict (==0.10.2)
